sparke_kinematics/__init__.py
sparke_kinematics/base_transformations.py
sparke_kinematics/leg_transformations.py
sparke_kinematics/sparke_base_IK.py
sparke_kinematics/sparke_leg_IK.py
sparke_kinematics/test_plotter.py
sparke_kinematics-0.0.1.dist-info/LICENSE
sparke_kinematics-0.0.1.dist-info/METADATA
sparke_kinematics-0.0.1.dist-info/WHEEL
sparke_kinematics-0.0.1.dist-info/top_level.txt
sparke_kinematics-0.0.1.dist-info/RECORD
