Metadata-Version: 2.1
Name: sparke-kinematics
Version: 0.0.1
Summary: Inverse and Forward Kinematics Solvers for Sparke Robot
Home-page: https://github.com/Infinite-Echo/sparkeKinematics
Author: Colin Fuelberth
Author-email: colin.fuelberth@icloud.com
License: MIT License
Keywords: sparke,sparke_kinematics,kinematics
Classifier: License :: OSI Approved :: MIT License
Classifier: Programming Language :: Python :: 3
License-File: LICENSE
Requires-Dist: numpy (>=1.24.0)
Requires-Dist: matplotlib (>=3.1.2)
